pyping2/__init__.py
pyping2/__main__.py
pyping2-0.1.2.dist-info/LICENSE
pyping2-0.1.2.dist-info/METADATA
pyping2-0.1.2.dist-info/WHEEL
pyping2-0.1.2.dist-info/top_level.txt
pyping2-0.1.2.dist-info/RECORD
