Metadata-Version: 2.1
Name: pyping2
Version: 0.1.2
Summary: An easy to use pinging tool
Home-page: https://github.com/awesomelewis2007/PyPing2/
Author: Lewis Evans
Author-email: awesomelewis2007@gmail.com
License: GNU
Platform: UNKNOWN
License-File: LICENSE
Requires-Dist: requests
